{
  "name": "client",
  "plural": "clients",
  "base": "PersistedModel",
  "idInjection": true,
  "options": {
    "validateUpsert": true
  },
  "properties": {
    "name": {
      "type": "string",
      "required": true
    },
    "password": {
      "type": "string",
      "required": true
    },
    "description": {
      "type": "string"
    },
    "email": {
      "type": "string",
      "required": true
    },
    "avatar": {
      "type": "string",
      "required": false
    }
  },
  "validations": [],
  "relations": {},
  "acls": [],
  "methods": {}
}
